__init__.py
toolchain-setup.py
toolchain/toolchain/python/ansi_escapes.py
toolchain/toolchain/python/base_config.py
toolchain/toolchain/python/component.py
toolchain/toolchain/python/device.py
toolchain/toolchain/python/hash_storage.py
toolchain/toolchain/python/import.py
toolchain/toolchain/python/includes.py
toolchain/toolchain/python/make_config.py
toolchain/toolchain/python/mod_structure.py
toolchain/toolchain/python/package.py
toolchain/toolchain/python/project_manager.py
toolchain/toolchain/python/script_build.py
toolchain/toolchain/python/shell.py
toolchain/toolchain/python/task.py
toolchain/toolchain/python/update.py
toolchain/toolchain/python/utils.py
toolchain/toolchain/python/workspace.py
toolchain/toolchain/python/java/java_build.py
toolchain/toolchain/python/native/native_build.py
toolchain/toolchain/python/native/native_setup.py
innercore_mod_toolchain-1664916402965.dist-info/METADATA
innercore_mod_toolchain-1664916402965.dist-info/WHEEL
innercore_mod_toolchain-1664916402965.dist-info/RECORD
