Metadata-Version: 2.1
Name: innercore-mod-toolchain
Version: 1664916402965
Summary: Inner Core Mod Toolchain for Horizon is a toolchain that allows you to efficiently develop and build modifications for mobile Minecraft: Bedrock Edition directly from your PC.
Project-URL: Homepage, https://github.com/zheka2304/innercore-mod-toolchain
Project-URL: Bug Tracker, https://github.com/zheka2304/innercore-mod-toolchain/issues
Author-email: zheka2304 <author@example.com>, MaXFeeD <author@example.com>, SDesya74 <author@example.com>, 80LK <author@example.com>, DMHYT <author@example.com>, ToxesFoxes <author@example.com>, DDShadowRU <author@example.com>, NikolaySavenko <author@example.com>
Classifier: Operating System :: OS Independent
Classifier: Programming Language :: Python :: 3
Requires-Python: >=3.7
